tests/__init__.py
tests/test_core.py
tests/test_utils.py
tra_algorithm/__init__.py
tra_algorithm/core.py
tra_algorithm/examples.py
tra_algorithm/utils.py
tra_algorithm/version.py
tra_algorithm-1.0.3.dist-info/LICENSE
tra_algorithm-1.0.3.dist-info/METADATA
tra_algorithm-1.0.3.dist-info/WHEEL
tra_algorithm-1.0.3.dist-info/top_level.txt
tra_algorithm-1.0.3.dist-info/RECORD
