Metadata-Version: 2.1
Name: tra-algorithm
Version: 1.0.3
Summary: Track/Rail Algorithm (TRA) - A novel machine learning algorithm for dynamic model selection
Home-page: https://github.com/eswaroy/tra_algorithm
Author: Dasari Ranga Eswar
Author-email: TRA Algorithm Team <contact@tra-algorithm.com>
License: MIT
Project-URL: Homepage, https://github.com/eswaroy/tra_algorithm
Project-URL: Bug Reports, https://github.com/eswaroy/tra_algorithm/issues
Project-URL: Source, https://github.com/eswaroy/tra_algorithm
Project-URL: Documentation, https://tra_algorithm.readthedocs.io/
Classifier: Development Status :: 4 - Beta
Classifier: Intended Audience :: Developers
Classifier: Intended Audience :: Science/Research
Classifier: License :: OSI Approved :: MIT License
Classifier: Operating System :: OS Independent
Classifier: Programming Language :: Python :: 3
Classifier: Programming Language :: Python :: 3.7
Classifier: Programming Language :: Python :: 3.8
Classifier: Programming Language :: Python :: 3.9
Classifier: Programming Language :: Python :: 3.10
Classifier: Programming Language :: Python :: 3.11
Classifier: Topic :: Scientific/Engineering :: Artificial Intelligence
Classifier: Topic :: Software Development :: Libraries :: Python Modules
Requires-Python: >=3.7
License-File: LICENSE
Requires-Dist: numpy>=1.19.0
Requires-Dist: pandas>=1.1.0
Requires-Dist: scikit-learn>=1.0.0
Requires-Dist: matplotlib>=3.3.0
Requires-Dist: joblib>=1.0.0
Requires-Dist: networkx>=2.5
Provides-Extra: dev
Requires-Dist: pytest>=6.0; extra == "dev"
Requires-Dist: pytest-cov>=2.10; extra == "dev"
Requires-Dist: black>=21.0; extra == "dev"
Requires-Dist: flake8>=3.8; extra == "dev"
Requires-Dist: sphinx>=4.0; extra == "dev"
Requires-Dist: sphinx-rtd-theme>=0.5; extra == "dev"
